gerrit_review.py
gerrit_review-0.1.0.dist-info/licenses/LICENSE
gerrit_review-0.1.0.dist-info/METADATA
gerrit_review-0.1.0.dist-info/WHEEL
gerrit_review-0.1.0.dist-info/entry_points.txt
gerrit_review-0.1.0.dist-info/top_level.txt
gerrit_review-0.1.0.dist-info/RECORD
