Metadata-Version: 2.4
Name: gerrit-review
Version: 0.1.0
Summary: A command-line tool to post review labels to Gerrit changes
Author: XuNeo
License: MIT
Project-URL: Homepage, https://github.com/XuNeo/gerrit-review
Project-URL: Repository, https://github.com/XuNeo/gerrit-review
Project-URL: Issues, https://github.com/XuNeo/gerrit-review/issues
Keywords: gerrit,code-review,ci,cli
Classifier: Development Status :: 4 - Beta
Classifier: Intended Audience :: Developers
Classifier: License :: OSI Approved :: MIT License
Classifier: Programming Language :: Python :: 3
Classifier: Programming Language :: Python :: 3.8
Classifier: Programming Language :: Python :: 3.9
Classifier: Programming Language :: Python :: 3.10
Classifier: Programming Language :: Python :: 3.11
Classifier: Programming Language :: Python :: 3.12
Classifier: Topic :: Software Development :: Build Tools
Classifier: Topic :: Software Development :: Version Control
Requires-Python: >=3.8
License-File: LICENSE
Requires-Dist: requests>=2.25.0
Provides-Extra: dev
Requires-Dist: pytest>=7.0; extra == "dev"
Requires-Dist: black>=22.0; extra == "dev"
Requires-Dist: flake8>=4.0; extra == "dev"
Dynamic: license-file
